example/__init__.py
example/nubia_context.py
example/nubia_example.py
example/nubia_plugin.py
example/nubia_statusbar.py
example/commands/__init__.py
example/commands/sample_commands.py
example/commands/more/__init__.py
example/commands/more/moar_commands.py
nubia/__init__.py
nubia/internal/__init__.py
nubia/internal/blackcmd.py
nubia/internal/cmdbase.py
nubia/internal/cmdloader.py
nubia/internal/completion.py
nubia/internal/constants.py
nubia/internal/context.py
nubia/internal/deprecation.py
nubia/internal/exceptions.py
nubia/internal/helpers.py
nubia/internal/interactive.py
nubia/internal/ipython.py
nubia/internal/nubia.py
nubia/internal/options.py
nubia/internal/parser.py
nubia/internal/plugin_interface.py
nubia/internal/registry.py
nubia/internal/registry_tools.py
nubia/internal/usage_logger_interface.py
nubia/internal/commands/__init__.py
nubia/internal/commands/builtin.py
nubia/internal/commands/help.py
nubia/internal/io/__init__.py
nubia/internal/io/eventbus.py
nubia/internal/io/logger.py
nubia/internal/io/session_logger.py
nubia/internal/typing/__init__.py
nubia/internal/typing/argparse.py
nubia/internal/typing/builder.py
nubia/internal/typing/inspect.py
nubia/internal/ui/__init__.py
nubia/internal/ui/ipython.py
nubia/internal/ui/lexer.py
nubia/internal/ui/statusbar.py
nubia/internal/ui/style.py
nubia_complete/__init__.py
nubia_complete/completer.py
nubia_complete/main.py
nubia_complete/shell.py
tests/empty_package/__init__.py
tests/sample_package/__init__.py
tests/sample_package/commands.py
tests/sample_package/subpackage/__init__.py
tests/sample_package/subpackage/more_commands.py
python_nubia-0.2b5.dist-info/LICENSE
python_nubia-0.2b5.dist-info/METADATA
python_nubia-0.2b5.dist-info/WHEEL
python_nubia-0.2b5.dist-info/entry_points.txt
python_nubia-0.2b5.dist-info/top_level.txt
python_nubia-0.2b5.dist-info/RECORD
