Metadata-Version: 2.1
Name: python-nubia
Version: 0.2b5
Summary: A framework for building beautiful shells
Home-page: https://github.com/facebookincubator/python-nubia
Author: Ahmed Soliman
Author-email: asoli@fb.com
License: UNKNOWN
Keywords: cli shell interactive framework
Platform: UNKNOWN
Classifier: Development Status :: 4 - Beta
Classifier: Intended Audience :: Developers
Classifier: Environment :: Console
Classifier: Programming Language :: Python :: 3.6
Classifier: Programming Language :: Python :: 3 :: Only
Classifier: Topic :: Software Development :: Libraries :: Python Modules
Classifier: License :: OSI Approved :: BSD License
Classifier: Operating System :: OS Independent
Requires-Python: >=3.6
Requires-Dist: jellyfish
Requires-Dist: prettytable
Requires-Dist: prompt-toolkit (>=2)
Requires-Dist: Pygments
Requires-Dist: pyparsing (>=2.2.0)
Requires-Dist: termcolor
Requires-Dist: typing-inspect
Requires-Dist: wcwidth
Requires-Dist: dataclasses ; python_version < "3.7"
